find_executable.py
find_executable-0.1.0a1.dist-info/licenses/LICENSE
find_executable-0.1.0a1.dist-info/METADATA
find_executable-0.1.0a1.dist-info/WHEEL
find_executable-0.1.0a1.dist-info/top_level.txt
find_executable-0.1.0a1.dist-info/RECORD
