Metadata-Version: 2.4
Name: find-executable
Version: 0.1.0a1
Summary: A Python package that provides cross-platform executable path resolution. Like Unix `which` command but better.
Author-email: Jifeng Wu <jifengwu2k@gmail.com>
License-Expression: MIT
Project-URL: Homepage, https://github.com/jifengwu2k/find-executable
Project-URL: Bug Tracker, https://github.com/jifengwu2k/find-executable/issues
Classifier: Programming Language :: Python :: 2
Classifier: Programming Language :: Python :: 3
Classifier: Operating System :: OS Independent
Requires-Python: >=2
License-File: LICENSE
Requires-Dist: posix-or-nt
Dynamic: license-file
